ostools/__init__.py
ostools/dirpath.py
ostools/exceptions.py
ostools/filepath.py
ostools/utils.py
ostools-1.1.8.dist-info/LICENSE.txt
ostools-1.1.8.dist-info/METADATA
ostools-1.1.8.dist-info/RECORD
ostools-1.1.8.dist-info/WHEEL
ostools-1.1.8.dist-info/top_level.txt
